cloudrecovery/__init__.py
cloudrecovery/__main__.py
cloudrecovery/cli.py
cloudrecovery/events.py
cloudrecovery/incident_detector.py
cloudrecovery/pty_runner.py
cloudrecovery/redact.py
cloudrecovery/server.py
cloudrecovery/settings.py
cloudrecovery/step_detector.py
cloudrecovery/agent/__init__.py
cloudrecovery/agent/config.py
cloudrecovery/agent/connection.py
cloudrecovery/agent/main.py
cloudrecovery/agent/collectors/host.py
cloudrecovery/agent/collectors/openshift.py
cloudrecovery/autopilot/__init__.py
cloudrecovery/autopilot/recovery_engine.py
cloudrecovery/autopilot/safety_monitor.py
cloudrecovery/autopilot/session_manager.py
cloudrecovery/ibm/__init__.py
cloudrecovery/ibm/automation.py
cloudrecovery/ibm/prompt_map.py
cloudrecovery/llm/__init__.py
cloudrecovery/llm/llm_provider.py
cloudrecovery/llm/model_catalog.py
cloudrecovery/llm/prompts.py
cloudrecovery/llm/settings.py
cloudrecovery/mcp/__init__.py
cloudrecovery/mcp/action_policy.py
cloudrecovery/mcp/host.py
cloudrecovery/mcp/mcp_server.py
cloudrecovery/mcp/openshift.py
cloudrecovery/mcp/policy.py
cloudrecovery/mcp/synthetics_tools.py
cloudrecovery/mcp/tools.py
cloudrecovery/notifications/__init__.py
cloudrecovery/notifications/email_notifier.py
cloudrecovery/notifications/models.py
cloudrecovery/runbooks/__init__.py
cloudrecovery/runbooks/executor.py
cloudrecovery/runbooks/registry.py
cloudrecovery/runbooks/schema.py
cloudrecovery/signals/__init__.py
cloudrecovery/signals/aggregator.py
cloudrecovery/signals/models.py
cloudrecovery/signals/synthetics.py
cloudrecovery/web/Footer.jsx
cloudrecovery/web/admin_dashboard.html
cloudrecovery/web/admin_dashboard.js
cloudrecovery/web/app.js
cloudrecovery/web/index.html
cloudrecovery/web/styles.css
cloudrecovery-0.1.1.dist-info/licenses/LICENSE
cloudrecovery-0.1.1.dist-info/METADATA
cloudrecovery-0.1.1.dist-info/WHEEL
cloudrecovery-0.1.1.dist-info/entry_points.txt
cloudrecovery-0.1.1.dist-info/top_level.txt
cloudrecovery-0.1.1.dist-info/RECORD
