Metadata-Version: 2.4
Name: cloudrecovery
Version: 0.1.1
Summary: CloudRecovery: enterprise incident response, monitoring, and autorecovery workspace (OpenShift + hybrid cloud).
Author: Ruslan Magana Vsevolodovna
License:                                  Apache License
Keywords: ibm-cloud,code-engine,container-registry,mcp,terminal,devops,automation,watsonx,ai,crewai
Classifier: Development Status :: 3 - Alpha
Classifier: Intended Audience :: Developers
Classifier: Intended Audience :: Information Technology
Classifier: License :: OSI Approved :: Apache Software License
Classifier: Programming Language :: Python :: 3
Classifier: Programming Language :: Python :: 3.11
Classifier: Topic :: Software Development :: Build Tools
Classifier: Topic :: System :: Systems Administration
Classifier: Topic :: Utilities
Requires-Python: <3.13,>=3.11
License-File: LICENSE
Requires-Dist: fastapi>=0.111.0
Requires-Dist: uvicorn[standard]>=0.30.0
Requires-Dist: httpx>=0.27.0
Requires-Dist: python-dotenv>=1.1.0
Requires-Dist: pydantic>=2.7.0
Requires-Dist: crewai[anthropic]>=0.76.9
Requires-Dist: anthropic>=0.39.0
Requires-Dist: crewai-tools>=0.13.4
Requires-Dist: ibm-watsonx-ai>=1.1.0
Requires-Dist: langchain-ibm>=0.3.0
Requires-Dist: rich>=13.0.0
Requires-Dist: pyjwt[crypto]>=2.8.0
Requires-Dist: litellm>=1.80.5
Requires-Dist: PyYAML>=6.0.1
Requires-Dist: psutil>=5.9.8
Requires-Dist: tenacity>=8.3.0
Requires-Dist: websockets>=12.0
Requires-Dist: aiosmtplib>=3.0.0
Provides-Extra: dev
Requires-Dist: pytest>=8.0; extra == "dev"
Requires-Dist: ruff>=0.5; extra == "dev"
Requires-Dist: twine>=5.0; extra == "dev"
Requires-Dist: build>=1.2.1; extra == "dev"
Dynamic: license-file
